nnwtable
